today/__init__.py
today/data_manupulation.py
today/paths.py
today/settings_manupulation.py
today/task_manupulation.py
today/theme_manupulation.py
today/time_formatting.py
today/today.py
today/todo.py
today/themes/matrix.json
today/themes/sunrise.json
today/themes/wob.json
today_cli-1.2.1.data/scripts/today
today_cli-1.2.1.dist-info/COPYING
today_cli-1.2.1.dist-info/METADATA
today_cli-1.2.1.dist-info/WHEEL
today_cli-1.2.1.dist-info/top_level.txt
today_cli-1.2.1.dist-info/RECORD
