Metadata-Version: 2.1
Name: today-cli
Version: 1.2.1
Summary: Command Line Day Planner
Home-page: https://github.com/TajwarHjkl/today/archive/refs/tags/v1.2.1.tar.gz
Author: Takey Tajwar
Author-email: tajwar.earth@proton.me
License: GPLv3
Classifier: Programming Language :: Python :: 3
Classifier: Operating System :: OS Independent
License-File: COPYING
